<?xml version = '1.0' encoding = 'UTF-8'?>
<Diagram class="oracle.dbtools.crest.swingui.relational.DPVRelational" name="Relational_1" id="523E626A-B07C-06EE-5D54-01A16B00797A">
<createdBy>Korisnik</createdBy>
<modifiedBy>Korisnik</modifiedBy>
<createdTime>2024-02-06 10:12:59 UTC</createdTime>
<autoRoute>false</autoRoute>
<boxInbox>true</boxInbox>
<showLegend>false</showLegend>
<showLabels>false</showLabels>
<showRelAttributes>false</showRelAttributes>
<gridEnabled>false</gridEnabled>
<showGrid>false</showGrid>
<diagramColor>-1</diagramColor>
<display>false</display>
<notation>1</notation>
<objectViews>
<OView class="oracle.dbtools.crest.swingui.relational.TVTable" oid="02833978-A29D-189D-285F-10E0D9237AD1" otype="Table" vid="C6CDA54A-8608-8CD3-6CD3-5F96897B49FF">
<hideElementsInCurrentOnly>false</hideElementsInCurrentOnly>
<bounds x="1160" y="874" width="235" height="130"/>
</OView>
<OView class="oracle.dbtools.crest.swingui.relational.TVTable" oid="02B904C6-BABE-C8FB-FD1E-82C867E3F85E" otype="Table" vid="4DC5C422-7011-CF75-ECD8-275E5D2B8DA6">
<hideElementsInCurrentOnly>false</hideElementsInCurrentOnly>
<bounds x="576" y="566" width="228" height="158"/>
</OView>
<OView class="oracle.dbtools.crest.swingui.relational.TVTable" oid="054F2691-8B19-6E88-92CD-6D4F2DB3F2D6" otype="Table" vid="A2719D91-FBD3-1D3D-C95B-BC8B3D4BD064">
<hideElementsInCurrentOnly>false</hideElementsInCurrentOnly>
<bounds x="274" y="1154" width="210" height="102"/>
</OView>
<OView class="oracle.dbtools.crest.swingui.relational.TVTable" oid="0945512B-BD57-76C9-CAD2-60D6742754A7" otype="Table" vid="D8E23A53-932B-5CCC-8626-9EB6008BA4B5">
<hideElementsInCurrentOnly>false</hideElementsInCurrentOnly>
<bounds x="20" y="1406" width="204" height="102"/>
</OView>
<OView class="oracle.dbtools.crest.swingui.relational.TVTable" oid="096BAEB8-3253-8F0C-CBDB-2C9D07824088" otype="Table" vid="E4B71012-0CEA-34AD-FBCF-DA0806D23DAF">
<hideElementsInCurrentOnly>false</hideElementsInCurrentOnly>
<bounds x="944" y="1938" width="181" height="88"/>
</OView>
<OView class="oracle.dbtools.crest.swingui.relational.TVTable" oid="0DBDEE34-B14F-34F1-2395-4B404BA65E46" otype="Table" vid="A5DC4E00-E579-B118-BACC-F4A83E595FE0">
<hideElementsInCurrentOnly>false</hideElementsInCurrentOnly>
<bounds x="2015" y="874" width="235" height="130"/>
</OView>
<OView class="oracle.dbtools.crest.swingui.relational.TVTable" oid="1901FC3A-334E-4DF2-A76D-56177020CADC" otype="Table" vid="16DEB9E9-2E66-8DB2-EEEA-F67118E034FF">
<hideElementsInCurrentOnly>false</hideElementsInCurrentOnly>
<bounds x="1973" y="566" width="235" height="130"/>
</OView>
<OView class="oracle.dbtools.crest.swingui.relational.TVTable" oid="1A68F123-A9FB-57E0-382B-3A2BC55DCD4F" otype="Table" vid="E87581F0-C0B5-225F-D3C0-15D305BC9178">
<hideElementsInCurrentOnly>false</hideElementsInCurrentOnly>
<bounds x="20" y="1938" width="181" height="88"/>
</OView>
<OView class="oracle.dbtools.crest.swingui.relational.TVTable" oid="1CBE8A5A-7A6B-3CDD-8D6E-1060D83D6549" otype="Table" vid="667E80A0-4BDB-6912-FFB8-D94C2FC4EFB1">
<hideElementsInCurrentOnly>false</hideElementsInCurrentOnly>
<bounds x="1045" y="1672" width="155" height="116"/>
</OView>
<OView class="oracle.dbtools.crest.swingui.relational.TVTable" oid="209DCA33-68CB-13E1-C44F-578499DBABA7" otype="Table" vid="EE93357A-5E41-753E-432A-DEE95B73600C">
<hideElementsInCurrentOnly>false</hideElementsInCurrentOnly>
<bounds x="1376" y="20" width="176" height="88"/>
</OView>
<OView class="oracle.dbtools.crest.swingui.relational.TVTable" oid="24264161-C15F-38D3-F106-273518BC6AC7" otype="Table" vid="9A94EEC1-DB33-9060-60CF-157741BA7BD1">
<hideElementsInCurrentOnly>false</hideElementsInCurrentOnly>
<bounds x="305" y="874" width="235" height="130"/>
</OView>
<OView class="oracle.dbtools.crest.swingui.relational.TVTable" oid="29360B12-C41B-8EA3-5565-F6DDB62DD5CE" otype="Table" vid="6D87D1AC-1D55-6E13-9BAD-F121BA6674E5">
<hideElementsInCurrentOnly>false</hideElementsInCurrentOnly>
<bounds x="20" y="1154" width="204" height="102"/>
</OView>
<OView class="oracle.dbtools.crest.swingui.relational.TVTable" oid="2ADC1C0A-55E6-9BCB-037C-E8184B340497" otype="Table" vid="720CECC5-8D42-D363-E1F3-59A01BD602A0">
<hideElementsInCurrentOnly>false</hideElementsInCurrentOnly>
<bounds x="875" y="874" width="235" height="130"/>
</OView>
<OView class="oracle.dbtools.crest.swingui.relational.TVTable" oid="2CC339F7-C3F7-FC6F-945B-464AA8291614" otype="Table" vid="233BC824-F123-C005-8153-A244BE58CEA2">
<hideElementsInCurrentOnly>false</hideElementsInCurrentOnly>
<bounds x="2324" y="1154" width="204" height="102"/>
</OView>
<OView class="oracle.dbtools.crest.swingui.relational.TVTable" oid="2E604AE4-2114-CABF-79C7-AE9A90B7AEF1" otype="Table" vid="816BCEF1-72F3-2F5F-3463-22F7C64E48C4">
<hideElementsInCurrentOnly>false</hideElementsInCurrentOnly>
<bounds x="482" y="1938" width="181" height="88"/>
</OView>
<OView class="oracle.dbtools.crest.swingui.relational.TVTable" oid="3B5924F0-108B-9D5A-7109-76197FCE364C" otype="Table" vid="AB38B699-8E34-290C-2444-BB11C57148B5">
<hideElementsInCurrentOnly>false</hideElementsInCurrentOnly>
<bounds x="246" y="258" width="176" height="88"/>
</OView>
<OView class="oracle.dbtools.crest.swingui.relational.TVTable" oid="3E210419-811A-60CB-03B9-C2DC706D2A12" otype="Table" vid="54498925-FFED-8F90-8D96-17B040DA8F78">
<hideElementsInCurrentOnly>false</hideElementsInCurrentOnly>
<bounds x="20" y="566" width="228" height="158"/>
</OView>
<OView class="oracle.dbtools.crest.swingui.relational.TVTable" oid="4154B66A-3720-0740-C461-20F587735604" otype="Table" vid="B7137049-3F32-6393-9514-A6919E3C7F19">
<hideElementsInCurrentOnly>false</hideElementsInCurrentOnly>
<bounds x="20" y="258" width="176" height="88"/>
</OView>
<OView class="oracle.dbtools.crest.swingui.relational.TVTable" oid="430E9890-D7FC-ADB2-4FE0-92CB197D3EC0" otype="Table" vid="C7D301F2-F807-1154-8DC3-92EAA9B34BC3">
<hideElementsInCurrentOnly>false</hideElementsInCurrentOnly>
<bounds x="1828" y="20" width="176" height="88"/>
</OView>
<OView class="oracle.dbtools.crest.swingui.relational.TVTable" oid="44A8B787-CFBB-0014-7480-8F9EB55A9005" otype="Table" vid="5CD49BC2-3E38-F5FA-EA75-EE7384EA828A">
<hideElementsInCurrentOnly>false</hideElementsInCurrentOnly>
<bounds x="2543" y="566" width="235" height="130"/>
</OView>
<OView class="oracle.dbtools.crest.swingui.relational.TVTable" oid="4698229E-2AB8-3398-E5E5-996F7526A317" otype="Table" vid="D4B88A3E-F306-23DB-6F9C-150DAA9F3E48">
<hideElementsInCurrentOnly>false</hideElementsInCurrentOnly>
<bounds x="298" y="566" width="228" height="158"/>
</OView>
<OView class="oracle.dbtools.crest.swingui.relational.TVTable" oid="47D70106-F8FC-7D5D-2504-1AB7B7715B39" otype="Table" vid="865DF1D5-219E-CBCE-F829-70942ED7B629">
<hideElementsInCurrentOnly>false</hideElementsInCurrentOnly>
<bounds x="698" y="258" width="228" height="158"/>
</OView>
<OView class="oracle.dbtools.crest.swingui.relational.TVTable" oid="4FAB4A62-8405-9894-7BD7-4A187D2E0930" otype="Table" vid="9FA5DB7B-091A-F522-A035-1F39A62BCE7A">
<hideElementsInCurrentOnly>false</hideElementsInCurrentOnly>
<bounds x="1445" y="874" width="235" height="130"/>
</OView>
<OView class="oracle.dbtools.crest.swingui.relational.TVTable" oid="5142BFEB-82F0-B482-0C6F-868043D92570" otype="Table" vid="FD8DBC2C-B094-9CE4-60EC-23F0065CE42C">
<hideElementsInCurrentOnly>false</hideElementsInCurrentOnly>
<bounds x="1784" y="1406" width="155" height="116"/>
</OView>
<OView class="oracle.dbtools.crest.swingui.relational.TVTable" oid="5804E201-AE3D-95D9-12CA-39638AACCB08" otype="Table" vid="DDE5F558-367B-1D1E-16CE-3AFFBB541CD4">
<hideElementsInCurrentOnly>false</hideElementsInCurrentOnly>
<bounds x="251" y="1938" width="181" height="88"/>
</OView>
<OView class="oracle.dbtools.crest.swingui.relational.TVTable" oid="590F2FC7-C843-CD11-C517-5765A17101B8" otype="Table" vid="06BB56F7-65C5-0137-9075-FD0273D92963">
<hideElementsInCurrentOnly>false</hideElementsInCurrentOnly>
<bounds x="2300" y="874" width="235" height="130"/>
</OView>
<OView class="oracle.dbtools.crest.swingui.relational.TVTable" oid="5A6BB845-0613-19EE-1AA2-0639BFC79A3C" otype="Table" vid="D3626FBD-5BF9-A844-E225-FDEE0679D559">
<hideElementsInCurrentOnly>false</hideElementsInCurrentOnly>
<bounds x="20" y="20" width="176" height="88"/>
</OView>
<OView class="oracle.dbtools.crest.swingui.relational.TVTable" oid="5B0AA8EA-F40E-5BE5-7227-B7FA6E7E11AF" otype="Table" vid="58410CB4-C792-3919-A506-DF86FC9128F8">
<hideElementsInCurrentOnly>false</hideElementsInCurrentOnly>
<bounds x="430" y="1672" width="155" height="116"/>
</OView>
<OView class="oracle.dbtools.crest.swingui.relational.TVTable" oid="5B31F18E-8A67-53FA-0284-FCFE03B367A5" otype="Table" vid="F24CCAC7-2536-85DD-1B8C-5273264C2B28">
<hideElementsInCurrentOnly>false</hideElementsInCurrentOnly>
<bounds x="1730" y="874" width="235" height="130"/>
</OView>
<OView class="oracle.dbtools.crest.swingui.relational.TVTable" oid="66FCC80B-0843-7748-C697-EC90AFC89F84" otype="Table" vid="811ADB15-2D26-3219-E625-3A0CAE86FB26">
<hideElementsInCurrentOnly>false</hideElementsInCurrentOnly>
<bounds x="1688" y="566" width="235" height="130"/>
</OView>
<OView class="oracle.dbtools.crest.swingui.relational.TVTable" oid="6800F316-9BDD-3610-BA3F-194E2B235428" otype="Table" vid="FA45B361-8BE3-8B1F-D0C6-E4345654F29F">
<hideElementsInCurrentOnly>false</hideElementsInCurrentOnly>
<bounds x="1481" y="1672" width="181" height="88"/>
</OView>
<OView class="oracle.dbtools.crest.swingui.relational.TVTable" oid="6B71BAFC-CFD2-4C00-2D42-CA5D4783E6A0" otype="Table" vid="C0E0D4FB-10D7-A31D-FF5D-56489B64DEE9">
<hideElementsInCurrentOnly>false</hideElementsInCurrentOnly>
<bounds x="1406" y="1938" width="181" height="88"/>
</OView>
<OView class="oracle.dbtools.crest.swingui.relational.TVTable" oid="6C0AC619-5DC6-7520-64BD-39D84F7716D5" otype="Table" vid="5A8FC77C-8CBB-C4CE-F867-B13E5BC28BC0">
<hideElementsInCurrentOnly>false</hideElementsInCurrentOnly>
<bounds x="1254" y="258" width="228" height="158"/>
</OView>
<OView class="oracle.dbtools.crest.swingui.relational.TVTable" oid="6FAF7CE9-EE9A-E4CC-98FC-6381181D39E7" otype="Table" vid="F17CFCF2-2432-5E40-D87D-ED87EF8F3D99">
<hideElementsInCurrentOnly>false</hideElementsInCurrentOnly>
<bounds x="1579" y="1406" width="155" height="116"/>
</OView>
<OView class="oracle.dbtools.crest.swingui.relational.TVTable" oid="73AD6FC1-3B3A-F95E-5322-0D9E44F686AF" otype="Table" vid="AC8C2AC8-CEC5-8826-45EA-6B5939A984AE">
<hideElementsInCurrentOnly>false</hideElementsInCurrentOnly>
<bounds x="1250" y="1672" width="181" height="88"/>
</OView>
<OView class="oracle.dbtools.crest.swingui.relational.TVTable" oid="77C9412A-398D-D9C8-3D4F-E5E05BF2F148" otype="Table" vid="55916DEE-4963-CC2F-859C-704724A671C7">
<hideElementsInCurrentOnly>false</hideElementsInCurrentOnly>
<bounds x="1532" y="258" width="228" height="158"/>
</OView>
<OView class="oracle.dbtools.crest.swingui.relational.TVTable" oid="78852F00-B951-AB7A-A6C2-E56F09F2A8FF" otype="Table" vid="F8342C87-92FB-6838-0866-EC65C1B469DF">
<hideElementsInCurrentOnly>false</hideElementsInCurrentOnly>
<bounds x="1816" y="1154" width="204" height="102"/>
</OView>
<OView class="oracle.dbtools.crest.swingui.relational.TVTable" oid="797BCDD4-0752-A9A2-9940-EE3C8BD2ACB0" otype="Table" vid="C27667CF-8490-6BB2-EB81-9ABAF5D15C07">
<hideElementsInCurrentOnly>false</hideElementsInCurrentOnly>
<bounds x="2258" y="566" width="235" height="130"/>
</OView>
<OView class="oracle.dbtools.crest.swingui.relational.TVTable" oid="7CDBA8F2-DE2E-E23D-C33C-A03E925B1277" otype="Table" vid="D65E6EF1-0047-8AAB-3324-090711E0FDCE">
<hideElementsInCurrentOnly>false</hideElementsInCurrentOnly>
<bounds x="759" y="1406" width="155" height="116"/>
</OView>
<OView class="oracle.dbtools.crest.swingui.relational.TVTable" oid="81D0BD20-693B-AA59-FEF9-9BEE7AFF3C7D" otype="Table" vid="FFBE7638-E136-0898-1700-9A0DDEB54EC4">
<hideElementsInCurrentOnly>false</hideElementsInCurrentOnly>
<bounds x="964" y="1406" width="155" height="116"/>
</OView>
<OView class="oracle.dbtools.crest.swingui.relational.TVTable" oid="82B49850-667C-4ED6-D4A5-A9E5CAEAF20C" otype="Table" vid="18B15FA8-5C6E-DF45-8A88-DF9793462A8A">
<hideElementsInCurrentOnly>false</hideElementsInCurrentOnly>
<bounds x="1169" y="1406" width="155" height="116"/>
</OView>
<OView class="oracle.dbtools.crest.swingui.relational.TVTable" oid="8DCD8EE7-8980-6383-2F54-16E2E1B99D6C" otype="Table" vid="64ECD4FD-A845-7149-DDEB-7EBAD7EB1101">
<hideElementsInCurrentOnly>false</hideElementsInCurrentOnly>
<bounds x="1810" y="258" width="228" height="158"/>
</OView>
<OView class="oracle.dbtools.crest.swingui.relational.TVTable" oid="900F4E68-EA52-A783-C032-E0572085753F" otype="Table" vid="8412F2F6-D4C0-270B-17F4-287BB1897527">
<hideElementsInCurrentOnly>false</hideElementsInCurrentOnly>
<bounds x="1602" y="20" width="176" height="88"/>
</OView>
<OView class="oracle.dbtools.crest.swingui.relational.TVTable" oid="90FBF64D-CD75-436B-F2B6-1A61A6CA3F9B" otype="Table" vid="DEFBD416-8224-7D46-6646-A00C0C20E48A">
<hideElementsInCurrentOnly>false</hideElementsInCurrentOnly>
<bounds x="528" y="1406" width="181" height="88"/>
</OView>
<OView class="oracle.dbtools.crest.swingui.relational.TVTable" oid="92A0B316-4085-0E75-36A9-A8447CDED73A" otype="Table" vid="1C60495B-A69D-333E-9EAB-57482EC380C5">
<hideElementsInCurrentOnly>false</hideElementsInCurrentOnly>
<bounds x="1989" y="1406" width="155" height="116"/>
</OView>
<OView class="oracle.dbtools.crest.swingui.relational.TVTable" oid="944160BB-23C2-9A2F-C4BA-12B14340452D" otype="Table" vid="DE1191A5-A45F-25A7-F4A9-6BCFD03C002F">
<hideElementsInCurrentOnly>false</hideElementsInCurrentOnly>
<bounds x="794" y="1154" width="210" height="102"/>
</OView>
<OView class="oracle.dbtools.crest.swingui.relational.TVTable" oid="9450FBEF-6F6B-925D-A3A4-4DC4CCECAA21" otype="Table" vid="5B331A3F-2189-BFD4-0D98-B46993674C98">
<hideElementsInCurrentOnly>false</hideElementsInCurrentOnly>
<bounds x="2070" y="1154" width="204" height="102"/>
</OView>
<OView class="oracle.dbtools.crest.swingui.relational.TVTable" oid="A04C6FBA-4FBC-430A-7056-5FBB51684FF8" otype="Table" vid="0AAD9B04-57D1-7082-14E1-66C0161597F1">
<hideElementsInCurrentOnly>false</hideElementsInCurrentOnly>
<bounds x="1712" y="1672" width="181" height="88"/>
</OView>
<OView class="oracle.dbtools.crest.swingui.relational.TVTable" oid="A1D41F9F-607D-E575-F0D1-394E14FE35F9" otype="Table" vid="FE1052F2-BFD1-C2C4-2ADE-5835DDA3E12D">
<hideElementsInCurrentOnly>false</hideElementsInCurrentOnly>
<bounds x="1943" y="1672" width="181" height="88"/>
</OView>
<OView class="oracle.dbtools.crest.swingui.relational.TVTable" oid="A4E91B04-206E-F9B0-BBE3-AC04B3E4DFAF" otype="Table" vid="FAD34F92-B50B-54E7-1905-B959892E5252">
<hideElementsInCurrentOnly>false</hideElementsInCurrentOnly>
<bounds x="1637" y="1938" width="181" height="88"/>
</OView>
<OView class="oracle.dbtools.crest.swingui.relational.TVTable" oid="A51683B5-7027-3C3D-EF86-D13BBB81E64F" otype="Table" vid="B8682C98-8C25-56DD-FE92-9820F8A6B204">
<hideElementsInCurrentOnly>false</hideElementsInCurrentOnly>
<bounds x="2585" y="874" width="195" height="102"/>
</OView>
<OView class="oracle.dbtools.crest.swingui.relational.TVTable" oid="A6504B14-64CF-0311-D6FC-0060B205D312" otype="Table" vid="F9D9BBBF-A72A-6C0E-B4E9-814F9F982305">
<hideElementsInCurrentOnly>false</hideElementsInCurrentOnly>
<bounds x="840" y="1672" width="155" height="116"/>
</OView>
<OView class="oracle.dbtools.crest.swingui.relational.TVTable" oid="B9CF86CD-6931-03CC-77F2-5B99355EA9A1" otype="Table" vid="EF0F44AA-471A-D2D4-1F90-D9CA8BE14D34">
<hideElementsInCurrentOnly>false</hideElementsInCurrentOnly>
<bounds x="590" y="874" width="235" height="130"/>
</OView>
<OView class="oracle.dbtools.crest.swingui.relational.TVTable" oid="C01D027E-DD7E-C8FD-7BA1-63D9BA4382C3" otype="Table" vid="CC758024-E2C7-D95A-83AD-A8A33BDF6E6C">
<hideElementsInCurrentOnly>false</hideElementsInCurrentOnly>
<bounds x="246" y="20" width="176" height="88"/>
</OView>
<OView class="oracle.dbtools.crest.swingui.relational.TVTable" oid="C3C832C9-BA46-C13F-4922-71EB974925AC" otype="Table" vid="233E98E8-7D5D-2417-D9DF-386D77C49069">
<hideElementsInCurrentOnly>false</hideElementsInCurrentOnly>
<bounds x="472" y="20" width="176" height="88"/>
</OView>
<OView class="oracle.dbtools.crest.swingui.relational.TVTable" oid="C4B6B1C9-55C9-F12A-EA4C-AA92895F991C" otype="Table" vid="BCF3346A-811D-E53A-C0A2-77BC6CC9E1DC">
<hideElementsInCurrentOnly>false</hideElementsInCurrentOnly>
<bounds x="635" y="1672" width="155" height="116"/>
</OView>
<OView class="oracle.dbtools.crest.swingui.relational.TVTable" oid="C5295515-3F60-29EC-7315-18D959B5EFC7" otype="Table" vid="C3371483-3CF2-6B55-2D3D-4A57C0E74852">
<hideElementsInCurrentOnly>false</hideElementsInCurrentOnly>
<bounds x="2054" y="20" width="176" height="88"/>
</OView>
<OView class="oracle.dbtools.crest.swingui.relational.TVTable" oid="C5297D74-6155-CA04-D74C-30A05F8DF41E" otype="Table" vid="0A4D1215-BA1B-7719-C564-52A424F5A88C">
<hideElementsInCurrentOnly>false</hideElementsInCurrentOnly>
<bounds x="1308" y="1154" width="204" height="102"/>
</OView>
<OView class="oracle.dbtools.crest.swingui.relational.TVTable" oid="C8D9C4F1-D732-FBDC-F0A1-171401857121" otype="Table" vid="0C5A3139-9D68-B86D-A433-7BA9E07A8AE8">
<hideElementsInCurrentOnly>false</hideElementsInCurrentOnly>
<bounds x="1132" y="566" width="228" height="158"/>
</OView>
<OView class="oracle.dbtools.crest.swingui.relational.TVTable" oid="CF890F64-13FF-EFFA-6D64-11C2424F3D07" otype="Table" vid="75EAA039-DB61-5CCA-1E95-051BB5D00311">
<hideElementsInCurrentOnly>false</hideElementsInCurrentOnly>
<bounds x="20" y="1672" width="155" height="116"/>
</OView>
<OView class="oracle.dbtools.crest.swingui.relational.TVTable" oid="D0165810-180D-264E-05EB-06F08812B5E7" otype="Table" vid="F04B1491-9C69-DEC2-A7C5-180ED6536024">
<hideElementsInCurrentOnly>false</hideElementsInCurrentOnly>
<bounds x="2088" y="258" width="228" height="158"/>
</OView>
<OView class="oracle.dbtools.crest.swingui.relational.TVTable" oid="D1E17FC4-31BD-C7B0-5589-E68F7CF755EC" otype="Table" vid="AA3FD817-9775-9DE3-3508-68647DCC023C">
<hideElementsInCurrentOnly>false</hideElementsInCurrentOnly>
<bounds x="472" y="258" width="176" height="88"/>
</OView>
<OView class="oracle.dbtools.crest.swingui.relational.TVTable" oid="D9485777-A44F-26F1-D409-6FBAB133BDC0" otype="Table" vid="D2489831-D130-0383-E894-A6766E14C726">
<hideElementsInCurrentOnly>false</hideElementsInCurrentOnly>
<bounds x="2366" y="258" width="228" height="158"/>
</OView>
<OView class="oracle.dbtools.crest.swingui.relational.TVTable" oid="DC294CB5-1A44-B8AE-6DFF-7933D4C08196" otype="Table" vid="C290B491-225E-D149-DAF7-4970F9941271">
<hideElementsInCurrentOnly>false</hideElementsInCurrentOnly>
<bounds x="976" y="258" width="228" height="158"/>
</OView>
<OView class="oracle.dbtools.crest.swingui.relational.TVTable" oid="DE360636-E6D3-4157-2F7E-FE80382E7504" otype="Table" vid="A4F7B1F0-2403-7CA5-3DAA-689A338A9852">
<hideElementsInCurrentOnly>false</hideElementsInCurrentOnly>
<bounds x="225" y="1672" width="155" height="116"/>
</OView>
<OView class="oracle.dbtools.crest.swingui.relational.TVTable" oid="DF9B0679-57C0-9CE0-41DE-B70E00E836C7" otype="Table" vid="324E56F5-03B1-AF32-F378-865F29A76ADF">
<hideElementsInCurrentOnly>false</hideElementsInCurrentOnly>
<bounds x="1175" y="1938" width="181" height="88"/>
</OView>
<OView class="oracle.dbtools.crest.swingui.relational.TVTable" oid="DFCBF7E7-8E02-2E6A-C4E3-437D2B6ADE22" otype="Table" vid="3D3881A7-0C44-E226-66D4-E9B07DE0E618">
<hideElementsInCurrentOnly>false</hideElementsInCurrentOnly>
<bounds x="20" y="874" width="235" height="130"/>
</OView>
<OView class="oracle.dbtools.crest.swingui.relational.TVTable" oid="E1D8CAA3-F249-2C9C-7DE4-CB1FB3FFA2D7" otype="Table" vid="00850F22-26D7-DEDB-69ED-6BC1D4445E8C">
<hideElementsInCurrentOnly>false</hideElementsInCurrentOnly>
<bounds x="534" y="1154" width="210" height="102"/>
</OView>
<OView class="oracle.dbtools.crest.swingui.relational.TVTable" oid="E31E5CBA-4CFC-A7DB-FE2A-6CA5052F9F1F" otype="Table" vid="D4D59AD7-E5F5-872E-4E73-1AF3B52961BB">
<hideElementsInCurrentOnly>false</hideElementsInCurrentOnly>
<bounds x="924" y="20" width="176" height="88"/>
</OView>
<OView class="oracle.dbtools.crest.swingui.relational.TVTable" oid="E3F8CF3D-B89E-CC1C-5C88-24B6ECC98D38" otype="Table" vid="0CBE6B5E-827F-7561-E409-224AD1D3D595">
<hideElementsInCurrentOnly>false</hideElementsInCurrentOnly>
<bounds x="1054" y="1154" width="204" height="102"/>
</OView>
<OView class="oracle.dbtools.crest.swingui.relational.TVTable" oid="E84D0788-C19B-8FCF-F311-2BCA3DBC03A5" otype="Table" vid="91129BD9-B5BE-A036-1D49-A98912635698">
<hideElementsInCurrentOnly>false</hideElementsInCurrentOnly>
<bounds x="1410" y="566" width="228" height="158"/>
</OView>
<OView class="oracle.dbtools.crest.swingui.relational.TVTable" oid="E93FB699-4E0D-E9B0-3AD3-DD4075922923" otype="Table" vid="0D78B5BC-463A-E1A6-0513-733B5D65E87D">
<hideElementsInCurrentOnly>false</hideElementsInCurrentOnly>
<bounds x="1562" y="1154" width="204" height="102"/>
</OView>
<OView class="oracle.dbtools.crest.swingui.relational.TVTable" oid="E9A30353-50BD-73EE-B9DC-6A86EBD93355" otype="Table" vid="5C718D90-5C18-159E-6F2E-5184EC7BC29D">
<hideElementsInCurrentOnly>false</hideElementsInCurrentOnly>
<bounds x="274" y="1406" width="204" height="102"/>
</OView>
<OView class="oracle.dbtools.crest.swingui.relational.TVTable" oid="E9DDCB01-14A5-9CEF-9037-3A5A61950D6E" otype="Table" vid="372C8046-4A9C-EC94-53F6-0635BCC7EE7B">
<hideElementsInCurrentOnly>false</hideElementsInCurrentOnly>
<bounds x="854" y="566" width="228" height="158"/>
</OView>
<OView class="oracle.dbtools.crest.swingui.relational.TVTable" oid="F4B89F1E-2CC6-ED41-3C15-175DD713C06F" otype="Table" vid="D3D335AA-63F8-E584-81CA-9C2927211839">
<hideElementsInCurrentOnly>false</hideElementsInCurrentOnly>
<bounds x="713" y="1938" width="181" height="88"/>
</OView>
<OView class="oracle.dbtools.crest.swingui.relational.TVTable" oid="F854169B-008E-31FA-CD80-8796B8DF107D" otype="Table" vid="6418ED5C-2844-AC1D-F064-A742663491E1">
<hideElementsInCurrentOnly>false</hideElementsInCurrentOnly>
<bounds x="1374" y="1406" width="155" height="116"/>
</OView>
<OView class="oracle.dbtools.crest.swingui.relational.TVTable" oid="F89FDDE4-8F71-6586-ACFC-613173FD4829" otype="Table" vid="3D4D943D-0354-C92D-14BB-36ACB4DB50D3">
<hideElementsInCurrentOnly>false</hideElementsInCurrentOnly>
<bounds x="698" y="20" width="176" height="88"/>
</OView>
<OView class="oracle.dbtools.crest.swingui.relational.TVTable" oid="FCC2A9F2-957C-13DB-0F21-8EECC13E62BA" otype="Table" vid="E19DE107-1EF6-A553-EDB1-1F7EC31FB25B">
<hideElementsInCurrentOnly>false</hideElementsInCurrentOnly>
<bounds x="1150" y="20" width="176" height="88"/>
</OView>
</objectViews>
</Diagram>